[
  {
    "_id": "604272e92628336a84278175",
    "title": "Frontend Web Development",
    "description": "Learn the fundamentals of frontend development, including HTML, CSS, JavaScript, version control, and popular frontend frameworks.",
    "weeks": 8,
    "tuition": 8000,
    "minimumSkill": "beginner",
    "bootcamp": "604144854e2a656528f63a45",
    "user": "60400c1c148cf728f47ccff5"
  },
  {
    "_id": "604272e92628336a84278176",
    "title": "Full Stack Web Development",
    "description": "Master full stack web development with frontend technologies and backend tools such as Node.js, Express, and MongoDB.",
    "weeks": 12,
    "tuition": 10000,
    "minimumSkill": "intermediate",
    "bootcamp": "604144854e2a656528f63a45",
    "user": "60400c1c148cf728f47ccff5"
  },
  {
    "_id": "604272e92628336a84278177",
    "title": "UI/UX Design",
    "description": "Learn how to design modern and user-friendly interfaces for web and mobile applications, combining design principles and development practices.",
    "weeks": 12,
    "tuition": 10000,
    "minimumSkill": "intermediate",
    "bootcamp": "604144854e2a656528f63a45",
    "user": "60400c1c148cf728f47ccff5"
  },
  {
    "_id": "604272e92628336a84278178",
    "title": "Web Design & Development",
    "description": "Get started building websites and web applications using HTML, CSS, JavaScript, and backend technologies.",
    "weeks": 10,
    "tuition": 9000,
    "minimumSkill": "beginner",
    "bootcamp": "6041edc7d34b6a547cd7b1cb",
    "user": "60408b786ef3ae60d09fa995"
  },
  {
    "_id": "604272e92628336a84278179",
    "title": "Data Science",
    "description": "Learn Python, data analysis, machine learning, and big data tools for real-world data science applications.",
    "weeks": 10,
    "tuition": 12000,
    "minimumSkill": "intermediate",
    "bootcamp": "6041edc7d34b6a547cd7b1cb",
    "user": "60408b786ef3ae60d09fa995"
  },
  {
    "_id": "6163109bdc9e494370dc5df3",
    "title": "Gardening Basics",
    "description": "Learn how to grow and care for flowers and plants, including practical gardening techniques.",
    "weeks": 15,
    "tuition": 5000,
    "minimumSkill": "beginner",
    "bootcamp": "6161ea3d5c1add21887bdc62",
    "user": "6161b71656f277401c47c0f5"
  }
]
